autobert/__init__.py
autobert/configuration_autobert.py
autobert/modeling_autobert.py
autobert/module/__init__.py
autobert/module/attn_layer.py
autobert/module/conv_layer.py
autobert-0.0.2.dist-info/METADATA
autobert-0.0.2.dist-info/WHEEL
autobert-0.0.2.dist-info/top_level.txt
autobert-0.0.2.dist-info/RECORD
